SecureFileRendering/__init__.py
SecureFileRendering/secure_file.py
SecureFileRendering-0.0.1.dist-info/LICENSE.txt
SecureFileRendering-0.0.1.dist-info/METADATA
SecureFileRendering-0.0.1.dist-info/WHEEL
SecureFileRendering-0.0.1.dist-info/top_level.txt
SecureFileRendering-0.0.1.dist-info/RECORD
