Metadata-Version: 2.1
Name: SecureFileRendering
Version: 0.0.1
Summary: A package for rendering file securely
Author-email: Souvik Mondal <mondalsouvik480@gmail.com>
License: Copyright (c) 2016 The Python Packaging Authority (PyPA)
Project-URL: Homepage, https://github.com/S-Mondal/SecureFileRendering
Keywords: file secure,secure render,file secure render,secure file render,setuptools,securefile
Classifier: Programming Language :: Python :: 3
Classifier: Operating System :: OS Independent
Requires-Python: >=3.8
License-File: LICENSE.txt
